<annotation>
	<folder>wyn1</folder>
	<filename>192.168.0.64_01_20200729174953349.jpg</filename>
	<path>C:\Users\51-9302\Desktop\oceanic dataset\wyn\wyn1\192.168.0.64_01_20200729174953349.jpg</path>
	<source>
		<database>Unknown</database>
	</source>
	<size>
		<width>1920</width>
		<height>1080</height>
		<depth>3</depth>
	</size>
	<segmented>0</segmented>
	<object>
		<name>boat</name>
		<pose>Unspecified</pose>
		<truncated>0</truncated>
		<difficult>0</difficult>
		<bndbox>
			<xmin>1072</xmin>
			<ymin>746</ymin>
			<xmax>1283</xmax>
			<ymax>834</ymax>
		</bndbox>
	</object>
	<object>
		<name>boat</name>
		<pose>Unspecified</pose>
		<truncated>0</truncated>
		<difficult>0</difficult>
		<bndbox>
			<xmin>742</xmin>
			<ymin>744</ymin>
			<xmax>776</xmax>
			<ymax>775</ymax>
		</bndbox>
	</object>
	<object>
		<name>ball</name>
		<pose>Unspecified</pose>
		<truncated>0</truncated>
		<difficult>0</difficult>
		<bndbox>
			<xmin>1426</xmin>
			<ymin>790</ymin>
			<xmax>1455</xmax>
			<ymax>819</ymax>
		</bndbox>
	</object>
	<object>
		<name>rubbish</name>
		<pose>Unspecified</pose>
		<truncated>0</truncated>
		<difficult>0</difficult>
		<bndbox>
			<xmin>590</xmin>
			<ymin>724</ymin>
			<xmax>628</xmax>
			<ymax>764</ymax>
		</bndbox>
	</object>
	<object>
		<name>rubbish</name>
		<pose>Unspecified</pose>
		<truncated>1</truncated>
		<difficult>0</difficult>
		<bndbox>
			<xmin>1</xmin>
			<ymin>701</ymin>
			<xmax>35</xmax>
			<ymax>731</ymax>
		</bndbox>
	</object>
</annotation>
