<annotation>
	<folder>hxx1</folder>
	<filename>192.168.0.64_01_2020090813271121.jpg</filename>
	<path>C:\Users\51-9302\Desktop\oceanic dataset\hxx\hxx1\192.168.0.64_01_2020090813271121.jpg</path>
	<source>
		<database>Unknown</database>
	</source>
	<size>
		<width>1920</width>
		<height>1080</height>
		<depth>3</depth>
	</size>
	<segmented>0</segmented>
	<object>
		<name>boat</name>
		<pose>Unspecified</pose>
		<truncated>0</truncated>
		<difficult>0</difficult>
		<bndbox>
			<xmin>601</xmin>
			<ymin>856</ymin>
			<xmax>624</xmax>
			<ymax>876</ymax>
		</bndbox>
	</object>
	<object>
		<name>rock</name>
		<pose>Unspecified</pose>
		<truncated>0</truncated>
		<difficult>0</difficult>
		<bndbox>
			<xmin>1201</xmin>
			<ymin>867</ymin>
			<xmax>1279</xmax>
			<ymax>879</ymax>
		</bndbox>
	</object>
	<object>
		<name>rock</name>
		<pose>Unspecified</pose>
		<truncated>0</truncated>
		<difficult>0</difficult>
		<bndbox>
			<xmin>980</xmin>
			<ymin>869</ymin>
			<xmax>1023</xmax>
			<ymax>895</ymax>
		</bndbox>
	</object>
	<object>
		<name>rock</name>
		<pose>Unspecified</pose>
		<truncated>0</truncated>
		<difficult>0</difficult>
		<bndbox>
			<xmin>1784</xmin>
			<ymin>846</ymin>
			<xmax>1813</xmax>
			<ymax>869</ymax>
		</bndbox>
	</object>
	<object>
		<name>rock</name>
		<pose>Unspecified</pose>
		<truncated>1</truncated>
		<difficult>0</difficult>
		<bndbox>
			<xmin>1869</xmin>
			<ymin>858</ymin>
			<xmax>1920</xmax>
			<ymax>874</ymax>
		</bndbox>
	</object>
	<object>
		<name>rock</name>
		<pose>Unspecified</pose>
		<truncated>0</truncated>
		<difficult>0</difficult>
		<bndbox>
			<xmin>1675</xmin>
			<ymin>860</ymin>
			<xmax>1729</xmax>
			<ymax>875</ymax>
		</bndbox>
	</object>
	<object>
		<name>rock</name>
		<pose>Unspecified</pose>
		<truncated>0</truncated>
		<difficult>0</difficult>
		<bndbox>
			<xmin>1112</xmin>
			<ymin>876</ymin>
			<xmax>1140</xmax>
			<ymax>889</ymax>
		</bndbox>
	</object>
</annotation>
