<annotation>
	<folder>hxx1</folder>
	<filename>192.168.0.64_01_20200908124344547.jpg</filename>
	<path>C:\Users\51-9302\Desktop\oceanic dataset\hxx\hxx1\192.168.0.64_01_20200908124344547.jpg</path>
	<source>
		<database>Unknown</database>
	</source>
	<size>
		<width>1920</width>
		<height>1080</height>
		<depth>3</depth>
	</size>
	<segmented>0</segmented>
	<object>
		<name>bridge</name>
		<pose>Unspecified</pose>
		<truncated>0</truncated>
		<difficult>0</difficult>
		<bndbox>
			<xmin>215</xmin>
			<ymin>598</ymin>
			<xmax>647</xmax>
			<ymax>643</ymax>
		</bndbox>
	</object>
	<object>
		<name>boat</name>
		<pose>Unspecified</pose>
		<truncated>0</truncated>
		<difficult>0</difficult>
		<bndbox>
			<xmin>1375</xmin>
			<ymin>593</ymin>
			<xmax>1492</xmax>
			<ymax>654</ymax>
		</bndbox>
	</object>
</annotation>
