<annotation>
	<folder>hxx1</folder>
	<filename>192.168.0.64_01_2020090813101493.jpg</filename>
	<path>C:\Users\51-9302\Desktop\oceanic dataset\hxx\hxx1\192.168.0.64_01_2020090813101493.jpg</path>
	<source>
		<database>Unknown</database>
	</source>
	<size>
		<width>1920</width>
		<height>1080</height>
		<depth>3</depth>
	</size>
	<segmented>0</segmented>
	<object>
		<name>harbor</name>
		<pose>Unspecified</pose>
		<truncated>0</truncated>
		<difficult>0</difficult>
		<bndbox>
			<xmin>114</xmin>
			<ymin>606</ymin>
			<xmax>412</xmax>
			<ymax>635</ymax>
		</bndbox>
	</object>
	<object>
		<name>boat</name>
		<pose>Unspecified</pose>
		<truncated>0</truncated>
		<difficult>0</difficult>
		<bndbox>
			<xmin>943</xmin>
			<ymin>602</ymin>
			<xmax>986</xmax>
			<ymax>632</ymax>
		</bndbox>
	</object>
	<object>
		<name>bridge</name>
		<pose>Unspecified</pose>
		<truncated>0</truncated>
		<difficult>0</difficult>
		<bndbox>
			<xmin>1093</xmin>
			<ymin>583</ymin>
			<xmax>1411</xmax>
			<ymax>619</ymax>
		</bndbox>
	</object>
</annotation>
