<annotation>
	<folder>yjb1</folder>
	<filename>192.168.0.64_01_20200727104107744.jpg</filename>
	<path>C:\Users\51-9302\Desktop\oceanic dataset\yjb\yjb1\192.168.0.64_01_20200727104107744.jpg</path>
	<source>
		<database>Unknown</database>
	</source>
	<size>
		<width>1920</width>
		<height>1080</height>
		<depth>3</depth>
	</size>
	<segmented>0</segmented>
	<object>
		<name>harbor</name>
		<pose>Unspecified</pose>
		<truncated>0</truncated>
		<difficult>0</difficult>
		<bndbox>
			<xmin>23</xmin>
			<ymin>835</ymin>
			<xmax>801</xmax>
			<ymax>1059</ymax>
		</bndbox>
	</object>
	<object>
		<name>boat</name>
		<pose>Unspecified</pose>
		<truncated>0</truncated>
		<difficult>0</difficult>
		<bndbox>
			<xmin>886</xmin>
			<ymin>368</ymin>
			<xmax>1148</xmax>
			<ymax>969</ymax>
		</bndbox>
	</object>
	<object>
		<name>ship</name>
		<pose>Unspecified</pose>
		<truncated>0</truncated>
		<difficult>0</difficult>
		<bndbox>
			<xmin>1180</xmin>
			<ymin>725</ymin>
			<xmax>1901</xmax>
			<ymax>931</ymax>
		</bndbox>
	</object>
	<object>
		<name>boat</name>
		<pose>Unspecified</pose>
		<truncated>0</truncated>
		<difficult>0</difficult>
		<bndbox>
			<xmin>842</xmin>
			<ymin>905</ymin>
			<xmax>970</xmax>
			<ymax>981</ymax>
		</bndbox>
	</object>
	<object>
		<name>boat</name>
		<pose>Unspecified</pose>
		<truncated>0</truncated>
		<difficult>0</difficult>
		<bndbox>
			<xmin>70</xmin>
			<ymin>187</ymin>
			<xmax>510</xmax>
			<ymax>962</ymax>
		</bndbox>
	</object>
</annotation>
