<annotation>
	<folder>sje1</folder>
	<filename>WIN_20200724_19_29_27_Pro.jpg</filename>
	<path>C:\Users\51-9302\Desktop\oceanic dataset\sje\sje1\WIN_20200724_19_29_27_Pro.jpg</path>
	<source>
		<database>Unknown</database>
	</source>
	<size>
		<width>3264</width>
		<height>1836</height>
		<depth>3</depth>
	</size>
	<segmented>0</segmented>
	<object>
		<name>rock</name>
		<pose>Unspecified</pose>
		<truncated>0</truncated>
		<difficult>0</difficult>
		<bndbox>
			<xmin>330</xmin>
			<ymin>1443</ymin>
			<xmax>601</xmax>
			<ymax>1645</ymax>
		</bndbox>
	</object>
	<object>
		<name>rock</name>
		<pose>Unspecified</pose>
		<truncated>0</truncated>
		<difficult>0</difficult>
		<bndbox>
			<xmin>620</xmin>
			<ymin>1359</ymin>
			<xmax>801</xmax>
			<ymax>1425</ymax>
		</bndbox>
	</object>
	<object>
		<name>rock</name>
		<pose>Unspecified</pose>
		<truncated>0</truncated>
		<difficult>0</difficult>
		<bndbox>
			<xmin>693</xmin>
			<ymin>1314</ymin>
			<xmax>806</xmax>
			<ymax>1380</ymax>
		</bndbox>
	</object>
	<object>
		<name>rock</name>
		<pose>Unspecified</pose>
		<truncated>0</truncated>
		<difficult>0</difficult>
		<bndbox>
			<xmin>809</xmin>
			<ymin>1325</ymin>
			<xmax>946</xmax>
			<ymax>1390</ymax>
		</bndbox>
	</object>
	<object>
		<name>rock</name>
		<pose>Unspecified</pose>
		<truncated>0</truncated>
		<difficult>0</difficult>
		<bndbox>
			<xmin>701</xmin>
			<ymin>1237</ymin>
			<xmax>818</xmax>
			<ymax>1316</ymax>
		</bndbox>
	</object>
	<object>
		<name>rock</name>
		<pose>Unspecified</pose>
		<truncated>0</truncated>
		<difficult>0</difficult>
		<bndbox>
			<xmin>592</xmin>
			<ymin>1273</ymin>
			<xmax>690</xmax>
			<ymax>1333</ymax>
		</bndbox>
	</object>
	<object>
		<name>rock</name>
		<pose>Unspecified</pose>
		<truncated>0</truncated>
		<difficult>0</difficult>
		<bndbox>
			<xmin>646</xmin>
			<ymin>1111</ymin>
			<xmax>937</xmax>
			<ymax>1216</ymax>
		</bndbox>
	</object>
	<object>
		<name>boat</name>
		<pose>Unspecified</pose>
		<truncated>0</truncated>
		<difficult>0</difficult>
		<bndbox>
			<xmin>1940</xmin>
			<ymin>837</ymin>
			<xmax>2035</xmax>
			<ymax>940</ymax>
		</bndbox>
	</object>
	<object>
		<name>boat</name>
		<pose>Unspecified</pose>
		<truncated>0</truncated>
		<difficult>0</difficult>
		<bndbox>
			<xmin>1813</xmin>
			<ymin>831</ymin>
			<xmax>1890</xmax>
			<ymax>930</ymax>
		</bndbox>
	</object>
	<object>
		<name>boat</name>
		<pose>Unspecified</pose>
		<truncated>0</truncated>
		<difficult>0</difficult>
		<bndbox>
			<xmin>1355</xmin>
			<ymin>856</ymin>
			<xmax>1426</xmax>
			<ymax>930</ymax>
		</bndbox>
	</object>
</annotation>
